{
    "sourceFile": "resources/views/livewire/escursioni-form.blade.php",
    "activeCommit": 0,
    "commits": [
        {
            "activePatchIndex": 3,
            "patches": [
                {
                    "date": 1719242315703,
                    "content": "Index: \n===================================================================\n--- \n+++ \n"
                },
                {
                    "date": 1719399672702,
                    "content": "Index: \n===================================================================\n--- \n+++ \n@@ -13,9 +13,9 @@\n                         @endforeach\n                     </select>\n                     <div class=\"error-message\">\n                         @error('excursionSelect')\n-                            <span class=\"text-danger\">{{ $message }}</span>\n+                            <span class=\"text-danger error\">{{ $message }}</span>\n                         @enderror\n                     </div>\n                 </div>\n             </div>\n@@ -26,9 +26,9 @@\n                     <input wire:model.live=\"excursionPassengers\" type=\"number\" class=\"form-control\"\n                         id=\"excursionPassengers\" min=\"1\" max=\"16\" value=\"1\">\n                     <div class=\"error-message\">\n                         @error('excursionPassengers')\n-                            <span class=\"text-danger\">{{ $message }}</span>\n+                            <span class=\"text-danger error\">{{ $message }}</span>\n                         @enderror\n                     </div>\n                 </div>\n                 <div class=\"col-6\">\n@@ -36,9 +36,9 @@\n                     <input wire:model.live=\"excursionDate\" type=\"datetime-local\" class=\"form-control\"\n                         id=\"dateExcursion\">\n                     <div class=\"error-message\">\n                         @error('excursionDate')\n-                            <span class=\"text-danger\">{{ $message }}</span>\n+                            <span class=\"text-danger error\">{{ $message }}</span>\n                         @enderror\n                     </div>\n                 </div>\n             </div>\n"
                },
                {
                    "date": 1719399797306,
                    "content": "Index: \n===================================================================\n--- \n+++ \n@@ -0,0 +1,58 @@\n+<div>\n+    <div class=\"container\">\n+        <form wire:submit.prevent=\"submitBookingExcursion\">\n+            <h4 class=\"text-uppercase text-danger\"><strong>Prenota Escursione</strong></h4>\n+            <div class=\"row\">\n+                <div class=\"col-12\">\n+                    <select wire:model.live=\"excursionSelect\" wire:change=\"calculatePriceExcursion\" id=\"excursionSelect\"\n+                        class=\"form-select\">\n+                        <option selected>Seleziona Escursione</option>\n+                        @foreach ($excursions as $excursion)\n+                            <option value=\"{{ $excursion->id }}\" data-price=\"{{ $excursion->price }}\">\n+                                {{ $excursion->name }}</option>\n+                        @endforeach\n+                    </select>\n+                    <div class=\"error-message\">\n+                        @error('excursionSelect')\n+                            <span class=\"text-danger error\">{{ $message }}</span>\n+                        @enderror\n+                    </div>\n+                </div>\n+            </div>\n+\n+            <div class=\"row\">\n+                <div class=\"col-6\">\n+                    <label for=\"excursionPassengers\" class=\"form-label\">Passeggeri</label>\n+                    <input wire:model.live=\"excursionPassengers\" type=\"number\" class=\"form-control\"\n+                        id=\"excursionPassengers\" min=\"1\" max=\"16\" value=\"1\">\n+                    <div class=\"error-message\">\n+                        @error('excursionPassengers')\n+                            <span class=\"text-danger error\">{{ $message }}</span>\n+                        @enderror\n+                    </div>\n+                </div>\n+                <div class=\"col-6\">\n+                    <label class=\"form-label\" for=\"dateExcursion\">Andata</label>\n+                    <input wire:model.live=\"excursionDate\" type=\"datetime-local\" class=\"form-control\"\n+                        id=\"dateExcursion\">\n+                    <div class=\"error-message\">\n+                        @error('excursionDate')\n+                            <span class=\"text-danger error\">{{ $message }}</span>\n+                        @enderror\n+                    </div>\n+                </div>\n+            </div>\n+\n+            <div class=\"row mb-3 align-items-end\">\n+                <div class=\"col-6\">\n+                    <label for=\"excursionPrice\" class=\"form-label\">Totale</label>\n+                    <input wire:model.live=\"excursionPrice\" readonly type=\"text\" class=\"form-control\"\n+                        id=\"excursionPrice\" value=\"\">\n+                </div>\n+                <div class=\"col-6 d-grid\">\n+                    <button type=\"submit\" class=\"btn bg-a text-white\">Prenota</button>\n+                </div>\n+            </div>\n+        </form>\n+    </div>\n+</div>\n"
                },
                {
                    "date": 1719495950198,
                    "content": "Index: \n===================================================================\n--- \n+++ \n@@ -1,8 +1,8 @@\n <div>\n     <div class=\"container\">\n         <form wire:submit.prevent=\"submitBookingExcursion\">\n-            <h4 class=\"text-uppercase text-danger\"><strong>Prenota Escursione</strong></h4>\n+            <h4 class=\"text-uppercase text-a\"><strong>Prenota Escursione</strong></h4>\n             <div class=\"row\">\n                 <div class=\"col-12\">\n                     <select wire:model.live=\"excursionSelect\" wire:change=\"calculatePriceExcursion\" id=\"excursionSelect\"\n                         class=\"form-select\">\n@@ -55,62 +55,4 @@\n             </div>\n         </form>\n     </div>\n </div>\n-<div>\n-    <div class=\"container\">\n-        <form wire:submit.prevent=\"submitBookingExcursion\">\n-            <h2 class=\"text-uppercase text-danger\"><strong>Prenota Escursione</strong></h2>\n-            <div class=\"row\">\n-                <div class=\"col-12\">\n-                    <select wire:model.live=\"excursionSelect\" wire:change=\"calculatePriceExcursion\" id=\"excursionSelect\"\n-                        class=\"form-select\">\n-                        <option selected>Seleziona Escursione</option>\n-                        @foreach ($excursions as $excursion)\n-                            <option value=\"{{ $excursion->id }}\" data-price=\"{{ $excursion->price }}\">\n-                                {{ $excursion->name }}</option>\n-                        @endforeach\n-                    </select>\n-                    <div class=\"error-message\">\n-                        @error('excursionSelect')\n-                            <span class=\"text-danger error\">{{ $message }}</span>\n-                        @enderror\n-                    </div>\n-                </div>\n-            </div>\n-\n-            <div class=\"row\">\n-                <div class=\"col-6\">\n-                    <label for=\"excursionPassengers\" class=\"form-label\">Passeggeri</label>\n-                    <input wire:model.live=\"excursionPassengers\" type=\"number\" class=\"form-control\"\n-                        id=\"excursionPassengers\" min=\"1\" max=\"16\" value=\"1\">\n-                    <div class=\"error-message\">\n-                        @error('excursionPassengers')\n-                            <span class=\"text-danger error\">{{ $message }}</span>\n-                        @enderror\n-                    </div>\n-                </div>\n-                <div class=\"col-6\">\n-                    <label class=\"form-label\" for=\"dateExcursion\">Andata</label>\n-                    <input wire:model.live=\"excursionDate\" type=\"datetime-local\" class=\"form-control\"\n-                        id=\"dateExcursion\">\n-                    <div class=\"error-message\">\n-                        @error('excursionDate')\n-                            <span class=\"text-danger error\">{{ $message }}</span>\n-                        @enderror\n-                    </div>\n-                </div>\n-            </div>\n-\n-            <div class=\"row mb-3 align-items-end\">\n-                <div class=\"col-6\">\n-                    <label for=\"excursionPrice\" class=\"form-label\">Totale</label>\n-                    <input wire:model.live=\"excursionPrice\" readonly type=\"text\" class=\"form-control\"\n-                        id=\"excursionPrice\" value=\"\">\n-                </div>\n-                <div class=\"col-6 d-grid\">\n-                    <button type=\"submit\" class=\"btn bg-a text-white\">Prenota</button>\n-                </div>\n-            </div>\n-        </form>\n-    </div>\n-</div>\n"
                }
            ],
            "date": 1719242315703,
            "name": "Commit-0",
            "content": "<div>\n    <div class=\"container\">\n        <form wire:submit.prevent=\"submitBookingExcursion\">\n            <h2 class=\"text-uppercase text-danger\"><strong>Prenota Escursione</strong></h2>\n            <div class=\"row\">\n                <div class=\"col-12\">\n                    <select wire:model.live=\"excursionSelect\" wire:change=\"calculatePriceExcursion\" id=\"excursionSelect\"\n                        class=\"form-select\">\n                        <option selected>Seleziona Escursione</option>\n                        @foreach ($excursions as $excursion)\n                            <option value=\"{{ $excursion->id }}\" data-price=\"{{ $excursion->price }}\">\n                                {{ $excursion->name }}</option>\n                        @endforeach\n                    </select>\n                    <div class=\"error-message\">\n                        @error('excursionSelect')\n                            <span class=\"text-danger\">{{ $message }}</span>\n                        @enderror\n                    </div>\n                </div>\n            </div>\n\n            <div class=\"row\">\n                <div class=\"col-6\">\n                    <label for=\"excursionPassengers\" class=\"form-label\">Passeggeri</label>\n                    <input wire:model.live=\"excursionPassengers\" type=\"number\" class=\"form-control\"\n                        id=\"excursionPassengers\" min=\"1\" max=\"16\" value=\"1\">\n                    <div class=\"error-message\">\n                        @error('excursionPassengers')\n                            <span class=\"text-danger\">{{ $message }}</span>\n                        @enderror\n                    </div>\n                </div>\n                <div class=\"col-6\">\n                    <label class=\"form-label\" for=\"dateExcursion\">Andata</label>\n                    <input wire:model.live=\"excursionDate\" type=\"datetime-local\" class=\"form-control\"\n                        id=\"dateExcursion\">\n                    <div class=\"error-message\">\n                        @error('excursionDate')\n                            <span class=\"text-danger\">{{ $message }}</span>\n                        @enderror\n                    </div>\n                </div>\n            </div>\n\n            <div class=\"row mb-3 align-items-end\">\n                <div class=\"col-6\">\n                    <label for=\"excursionPrice\" class=\"form-label\">Totale</label>\n                    <input wire:model.live=\"excursionPrice\" readonly type=\"text\" class=\"form-control\"\n                        id=\"excursionPrice\" value=\"\">\n                </div>\n                <div class=\"col-6 d-grid\">\n                    <button type=\"submit\" class=\"btn bg-a text-white\">Prenota</button>\n                </div>\n            </div>\n        </form>\n    </div>\n</div>\n"
        }
    ]
}